geometricus/__init__.py
geometricus/geometricus.py
geometricus/moment_utility.py
geometricus/protein_utility.py
geometricus-0.3.0.dist-info/LICENSE
geometricus-0.3.0.dist-info/METADATA
geometricus-0.3.0.dist-info/WHEEL
geometricus-0.3.0.dist-info/top_level.txt
geometricus-0.3.0.dist-info/RECORD
