Metadata-Version: 2.1
Name: geometricus
Version: 0.3.0
Summary: Fast, structure-based, alignment-free protein embedding
Home-page: https://github.com/TurtleTools/geometricus
Author: Janani Durairaj, Mehmet Akdel
Author-email: janani.durairaj@unibas.ch
License: MIT License
Platform: UNKNOWN
Classifier: Intended Audience :: Science/Research
Classifier: License :: OSI Approved :: MIT License
Classifier: Programming Language :: Python
Classifier: Programming Language :: Python :: 3
Classifier: Programming Language :: Python :: 3.7
Classifier: Topic :: Scientific/Engineering
Classifier: Operating System :: Microsoft :: Windows
Classifier: Operating System :: POSIX
Classifier: Operating System :: Unix
Classifier: Operating System :: MacOS
License-File: LICENSE
Requires-Dist: numpy (==1.21.5)
Requires-Dist: scipy
Requires-Dist: numba (==0.55.1)
Requires-Dist: prody
